MIPS_32.v
module pipe_MIPS32 (clk1, clk2);
    input clk1, clk2; // Two-phase clock
  
    reg [31:0] PC, IF_ID_IR, IF_ID_NPC;
    reg [31:0] ID_EX_IR, ID_EX_NPC, ID_EX_A, ID_EX_B, ID_EX_Imm;
    reg [2:0] ID_EX_type, EX_MEM_type, MEM_WB_type;
    reg [31:0] EX_MEM_IR, EX_MEM_ALUOut, EX_MEM_B;
    reg EX_MEM_cond;
    reg [31:0] MEM_WB_IR, MEM_WB_ALUOut, MEM_WB_LMD;
    
    reg [31:0] Reg [0:31]; // Register bank (32 x 32)
    reg [31:0] Mem [0:1023]; // 1024 x 32 memory
    
    parameter ADD = 6'b000000, SUB = 6'b000001, AND = 6'b000010, OR = 6'b000011,
              SLT = 6'b000100, MUL = 6'b000101, HLT = 6'b111111, LW = 6'b100000,
              SW = 6'b100001, ADDI = 6'b001010, SUBI = 6'b001011, SLTI = 6'b001100,
              BNEQZ = 6'b001101, BEQZ = 6'b001110;

    parameter RR_ALU = 3'b000, RM_ALU = 3'b001, LOAD = 3'b010, STORE = 3'b011,
              BRANCH = 3'b100, HALT = 3'b101;            
    
    reg HALTED; // Set after HLT instruction is completed (in WB stage)
    reg TAKEN_BRANCH; // Required to disable instructions after branch

    always @(posedge clk1) // IF Stage
        if (HALTED == 0) begin
            if (((EX_MEM_IR[31:26] == BEQZ) && (EX_MEM_cond == 1)) ||
                ((EX_MEM_IR[31:26] == BNEQZ) && (EX_MEM_cond == 0))) begin
                IF_ID_IR <= #2 Mem[EX_MEM_ALUOut];
                TAKEN_BRANCH <= #2 1'b1;
                IF_ID_NPC <= #2 EX_MEM_ALUOut + 1;
                PC <= #2 EX_MEM_ALUOut + 1;
            end else begin
                IF_ID_IR <= #2 Mem[PC];
                IF_ID_NPC <= #2 PC + 1;
                PC <= #2 PC + 1;
            end
        end

    always @(posedge clk2) // ID Stage
        if (HALTED == 0) begin
            if (IF_ID_IR[25:21] == 5'b00000) 
                ID_EX_A <= 0;
            else 
                ID_EX_A <= #2 Reg[IF_ID_IR[25:21]]; // "rs"
            if (IF_ID_IR[20:16] == 5'b00000) 
                ID_EX_B <= 0;
            else 
                ID_EX_B <= #2 Reg[IF_ID_IR[20:16]]; // "rt"
            
            ID_EX_NPC <= #2 IF_ID_NPC;
            ID_EX_IR <= #2 IF_ID_IR;
            ID_EX_Imm <= #2 {{16{IF_ID_IR[15]}}, {IF_ID_IR[15:0]}};
            
            case (IF_ID_IR[31:26])
                ADD, SUB, AND, OR, SLT, MUL: ID_EX_type <= #2 RR_ALU;
                ADDI, SUBI, SLTI: ID_EX_type <= #2 RM_ALU;
                LW: ID_EX_type <= #2 LOAD;
                SW: ID_EX_type <= #2 STORE;
                BNEQZ, BEQZ: ID_EX_type <= #2 BRANCH;
                HLT: ID_EX_type <= #2 HALT;
                default: ID_EX_type <= #2 HALT; // Invalid opcode
            endcase
        end

    always @(posedge clk1) // EX Stage
        if (HALTED == 0) begin
            EX_MEM_type <= #2 ID_EX_type;
            EX_MEM_IR <= #2 ID_EX_IR;
            TAKEN_BRANCH <= #2 0;
            case (ID_EX_type)
                RR_ALU: begin
                    case (ID_EX_IR[31:26]) // "opcode"
                        ADD: EX_MEM_ALUOut <= #2 ID_EX_A + ID_EX_B;
                        SUB: EX_MEM_ALUOut <= #2 ID_EX_A - ID_EX_B;
                        AND: EX_MEM_ALUOut <= #2 ID_EX_A & ID_EX_B;
                        OR: EX_MEM_ALUOut <= #2 ID_EX_A | ID_EX_B;
                        SLT: EX_MEM_ALUOut <= #2 (ID_EX_A < ID_EX_B);
                        MUL: EX_MEM_ALUOut <= #2 ID_EX_A * ID_EX_B;
                        default: EX_MEM_ALUOut <= #2 32'hxxxxxxxx;
                    endcase
                end
                RM_ALU: begin
                    case (ID_EX_IR[31:26]) // "opcode"
                        ADDI: EX_MEM_ALUOut <= #2 ID_EX_A + ID_EX_Imm;
                        SUBI: EX_MEM_ALUOut <= #2 ID_EX_A - ID_EX_Imm;
                        SLTI: EX_MEM_ALUOut <= #2 (ID_EX_A < ID_EX_Imm);
                        default: EX_MEM_ALUOut <= #2 32'hxxxxxxxx;
                    endcase
                end        
                LOAD, STORE: begin
                    EX_MEM_ALUOut <= #2 ID_EX_A + ID_EX_Imm;
                    EX_MEM_B <= #2 ID_EX_B;
                end
                BRANCH: begin
                    EX_MEM_ALUOut <= #2 ID_EX_NPC + ID_EX_Imm;
                    EX_MEM_cond <= #2 (ID_EX_A == 0);
                end
            endcase
        end  

    always @(posedge clk2) // MEM Stage
        if (HALTED == 0) begin
            MEM_WB_type <= EX_MEM_type;
            MEM_WB_IR <= #2 EX_MEM_IR;
            case (EX_MEM_type)
                RR_ALU, RM_ALU: MEM_WB_ALUOut <= #2 EX_MEM_ALUOut;
                LOAD: MEM_WB_LMD <= #2 Mem[EX_MEM_ALUOut];
                STORE: if (TAKEN_BRANCH == 0) // Disable write
                    Mem[EX_MEM_ALUOut] <= #2 EX_MEM_B;
            endcase
        end

    always @(posedge clk1) // WB Stage
        begin
            if (TAKEN_BRANCH == 0) // Disable write if branch taken
            case (MEM_WB_type)
                RR_ALU: Reg[MEM_WB_IR[15:11]] <= #2 MEM_WB_ALUOut; // "rd"
                RM_ALU: Reg[MEM_WB_IR[20:16]] <= #2 MEM_WB_ALUOut; // "rt"
                LOAD: Reg[MEM_WB_IR[20:16]] <= #2 MEM_WB_LMD; // "rt"
                HALT: HALTED <= #2 1'b1;
            endcase
        end
endmodule

MIPS_32_tb_3.v
module test_mips32_3;
    reg clk1, clk2;
    integer k;
    pipe_MIPS32 mips (clk1, clk2);
        initial
            begin
                clk1 = 0; clk2 = 0;
                repeat (50) // Generating two-phase clock
                    begin
                        #5 clk1 = 1; #5 clk1 = 0;
                        #5 clk2 = 1; #5 clk2 = 0;
                    end
            end

        initial
            begin
                for (k=0; k<31; k=k+1)
                        mips.Reg[k] = k;

                        mips.Mem[0] = 32'h280a00c8; // ADDI R10,R0,200
                        mips.Mem[1] = 32'h28020001; // ADDI R2,R0,1
                        mips.Mem[2] = 32'h0e94a000; // OR R20,R20,R20 -- dummy instr.
                        mips.Mem[3] = 32'h21430000; // LW R3,0(R10)
                        mips.Mem[4] = 32'h0e94a000; // OR R20,R20,R20 -- dummy instr.
                        mips.Mem[5] = 32'h14431000; // Loop: MUL R2,R2,R3
                        mips.Mem[6] = 32'h2c630001; // SUBI R3,R3,1
                        mips.Mem[7] = 32'h0e94a000; // OR R20,R20,R20 -- dummy instr.
                        mips.Mem[8] = 32'h3460fffc; // BNEQZ R3,Loop (i.e. -4 offset)
                        mips.Mem[9] = 32'h2542fffe; // SW R2,-2(R10)
                        mips.Mem[10] = 32'hfc000000; // HLT   
                    
                        mips.Mem[200] = 7; // Find factorial of 7
                        mips.PC = 0;
                        mips.HALTED = 0;
                        mips.TAKEN_BRANCH = 0;
                        #2000 $display ("Mem[200] = %2d, Mem[198] = %6d",
                        mips.Mem[200], mips.Mem[198]);
            end     
        initial
            begin
                $dumpfile ("mips_3.vcd");
                $dumpvars (0, test_mips32_3);
                $monitor ("R2: %4d", mips.Reg[2]);
                #3000 $finish;
            end
endmodule

mips_3.vcd
$date
	Sun Jan 05 11:05:44 2025
$end
$version
	Icarus Verilog
$end
$timescale
	1s
$end
$scope module test_mips32_3 $end
$var reg 1 ! clk1 $end
$var reg 1 " clk2 $end
$var integer 32 # k [31:0] $end
$scope module mips $end
$var wire 1 $ clk1 $end
$var wire 1 % clk2 $end
$var reg 32 & EX_MEM_ALUOut [31:0] $end
$var reg 32 ' EX_MEM_B [31:0] $end
$var reg 32 ( EX_MEM_IR [31:0] $end
$var reg 1 ) EX_MEM_cond $end
$var reg 3 * EX_MEM_type [2:0] $end
$var reg 1 + HALTED $end
$var reg 32 , ID_EX_A [31:0] $end
$var reg 32 - ID_EX_B [31:0] $end
$var reg 32 . ID_EX_IR [31:0] $end
$var reg 32 / ID_EX_Imm [31:0] $end
$var reg 32 0 ID_EX_NPC [31:0] $end
$var reg 3 1 ID_EX_type [2:0] $end
$var reg 32 2 IF_ID_IR [31:0] $end
$var reg 32 3 IF_ID_NPC [31:0] $end
$var reg 32 4 MEM_WB_ALUOut [31:0] $end
$var reg 32 5 MEM_WB_IR [31:0] $end
$var reg 32 6 MEM_WB_LMD [31:0] $end
$var reg 3 7 MEM_WB_type [2:0] $end
$var reg 32 8 PC [31:0] $end
$var reg 1 9 TAKEN_BRANCH $end
$upscope $end
$upscope $end
$enddefinitions $end
#0
$dumpvars
09
b0 8
bx 7
bx 6
bx 5
bx 4
bx 3
bx 2
bx 1
bx 0
bx /
bx .
bx -
bx ,
0+
bx *
x)
bx (
bx '
bx &
0%
0$
b11111 #
0"
0!
$end
#5
1!
1$
#7
b1 8
b1 3
b101000000010100000000011001000 2
#10
0!
0$
#15
b0 ,
1"
1%
#17
b1 1
b11001000 /
b101000000010100000000011001000 .
b1 0
b1010 -
#20
0"
0%
#25
1!
1$
#27
b11001000 &
b101000000010100000000011001000 (
b1 *
b10 8
b10 3
b101000000000100000000000000001 2
#30
0!
0$
#35
b1 7
1"
1%
#37
b11001000 4
b101000000010100000000011001000 5
b1 /
b101000000000100000000000000001 .
b10 0
b10 -
#40
0"
0%
#45
1!
1$
#47
b11 8
b11 3
b1110100101001010000000000000 2
b1 &
b101000000000100000000000000001 (
#50
0!
0$
#55
1"
1%
#57
b0 1
b11111111111111111010000000000000 /
b1110100101001010000000000000 .
b11 0
b10100 -
b10100 ,
b1 4
b101000000000100000000000000001 5
#60
0"
0%
#65
1!
1$
#67
b10100 &
b1110100101001010000000000000 (
b0 *
b100 8
b100 3
b100001010000110000000000000000 2
#70
0!
0$
#75
b0 7
1"
1%
#77
b10100 4
b1110100101001010000000000000 5
b101 1
b0 /
b100001010000110000000000000000 .
b100 0
b11 -
b11001000 ,
#80
0"
0%
#85
1!
1$
#87
b101 8
b101 3
b1110100101001010000000000000 2
b100001010000110000000000000000 (
b101 *
#90
0!
0$
#95
b101 7
1"
1%
#97
b0 1
b11111111111111111010000000000000 /
b1110100101001010000000000000 .
b101 0
b10100 -
b10100 ,
b100001010000110000000000000000 5
#100
0"
0%
#105
1!
1$
#107
1+
b1110100101001010000000000000 (
b0 *
b110 8
b110 3
b10100010000110001000000000000 2
